python_searchlightclient-2.1.1.dist-info/DESCRIPTION.rst
python_searchlightclient-2.1.1.dist-info/METADATA
python_searchlightclient-2.1.1.dist-info/RECORD
python_searchlightclient-2.1.1.dist-info/WHEEL
python_searchlightclient-2.1.1.dist-info/entry_points.txt
python_searchlightclient-2.1.1.dist-info/metadata.json
python_searchlightclient-2.1.1.dist-info/pbr.json
python_searchlightclient-2.1.1.dist-info/top_level.txt
searchlightclient/__init__.py
searchlightclient/client.py
searchlightclient/exc.py
searchlightclient/i18n.py
searchlightclient/common/__init__.py
searchlightclient/common/base.py
searchlightclient/common/exceptions.py
searchlightclient/common/utils.py
searchlightclient/osc/__init__.py
searchlightclient/osc/plugin.py
searchlightclient/osc/v1/__init__.py
searchlightclient/osc/v1/facet.py
searchlightclient/osc/v1/resource_type.py
searchlightclient/osc/v1/search.py
searchlightclient/tests/__init__.py
searchlightclient/tests/unit/__init__.py
searchlightclient/tests/unit/osc/__init__.py
searchlightclient/tests/unit/osc/fakes.py
searchlightclient/tests/unit/osc/utils.py
searchlightclient/tests/unit/osc/v1/__init__.py
searchlightclient/tests/unit/osc/v1/fakes.py
searchlightclient/tests/unit/osc/v1/test_facet.py
searchlightclient/tests/unit/osc/v1/test_resource_type.py
searchlightclient/tests/unit/osc/v1/test_search.py
searchlightclient/tests/unit/v1/__init__.py
searchlightclient/tests/unit/v1/test_facets.py
searchlightclient/tests/unit/v1/test_resource_types.py
searchlightclient/tests/unit/v1/test_search.py
searchlightclient/v1/__init__.py
searchlightclient/v1/client.py
searchlightclient/v1/facets.py
searchlightclient/v1/resource_types.py
searchlightclient/v1/search.py
